Metadata-Version: 2.1
Name: bib-vk-bots
Version: 0.1
Requires-Dist: vk-api
